djorm_pool/__init__.py
django_orm_pool-2021.1.dist-info/LICENSE
django_orm_pool-2021.1.dist-info/METADATA
django_orm_pool-2021.1.dist-info/WHEEL
django_orm_pool-2021.1.dist-info/top_level.txt
django_orm_pool-2021.1.dist-info/RECORD
