Metadata-Version: 2.1
Name: django-orm-pool
Version: 2021.1
Summary: DB-API2 connection pool for Django (for postgresql, mysql and sqlite)
Home-page: https://github.com/djangonauts/djorm-ext-pool
Author: Andrey Antukh
Author-email: niwi@niwi.be
Maintainer: Andrey Antukh
Maintainer-email: niwi@niwi.be
License: BSD
Platform: OS Independent
Classifier: Development Status :: 5 - Production/Stable
Classifier: Framework :: Django
Classifier: Intended Audience :: Developers
Classifier: License :: OSI Approved :: BSD License
Classifier: Operating System :: OS Independent
Classifier: Programming Language :: Python
Classifier: Topic :: Internet :: WWW/HTTP
License-File: LICENSE
Requires-Dist: sqlalchemy (>=1.3.3)
